passrule/__init__.py
passrule/generator.py
passrule/validator.py
passrule-0.1.2.dist-info/METADATA
passrule-0.1.2.dist-info/WHEEL
passrule-0.1.2.dist-info/licenses/LICENSE
passrule-0.1.2.dist-info/RECORD
