Metadata-Version: 2.4
Name: passrule
Version: 0.1.2
Summary: 可配置的密码校验库
Project-URL: Homepage, https://github.com/hongchou/passrule
Project-URL: Repository, https://github.com/hongchou/passrule
Author-email: "chouhong2021@163.com" <chouhong2021@163.com>
License-Expression: MIT
License-File: LICENSE
Classifier: Development Status :: 4 - Beta
Classifier: Intended Audience :: Developers
Classifier: License :: OSI Approved :: MIT License
Classifier: Programming Language :: Python :: 3
Classifier: Programming Language :: Python :: 3.8
Classifier: Programming Language :: Python :: 3.9
Classifier: Programming Language :: Python :: 3.10
Classifier: Programming Language :: Python :: 3.11
Classifier: Programming Language :: Python :: 3.12
Requires-Python: >=3.8
